{
    "prepare_queue": {
        "installed": [],
        "uninstalled": []
    },
    "config_munge": {
        "files": {}
    },
    "installed_plugins": {
        "cordova-plugin-device": {
            "PACKAGE_NAME": "com.msruu.vera"
        },
        "cordova-plugin-dialogs": {
            "PACKAGE_NAME": "com.msruu.vera"
        },
        "cordova-plugin-statusbar": {
            "PACKAGE_NAME": "com.msruu.vera"
        },
        "cordova-plugin-whitelist": {
            "PACKAGE_NAME": "com.msruu.vera"
        },
        "onesignal-cordova-plugin": {
            "PACKAGE_NAME": "com.msruu.vera"
        }
    },
    "dependent_plugins": {}
}